pypipeline/__init__.py
pypipeline/experiment_runner.py
pypipeline/pipeline.py
pypipeline/qsub.py
pypipeline/relauncher.py
pypipeline/remote_prep.py
pypipeline/scrape.py
pypipeline/stages.py
pypipeline/topological.py
pypipeline/util.py
pypipeline-0.1.1.data/scripts/relaunch.py
pypipeline-0.1.1.data/scripts/scrape_exps.py
pypipeline-0.1.1.dist-info/DESCRIPTION.rst
pypipeline-0.1.1.dist-info/METADATA
pypipeline-0.1.1.dist-info/RECORD
pypipeline-0.1.1.dist-info/WHEEL
pypipeline-0.1.1.dist-info/metadata.json
pypipeline-0.1.1.dist-info/top_level.txt
