Metadata-Version: 2.0
Name: pypipeline
Version: 0.1.1
Summary: Python scripts for running pipelines of experiments locally or on Sun Grid Engine.
Home-page: https://github.com/mgormley/pypipeline
Author: Matt Gormley
Author-email: mrg@cs.jhu.edu
License: MIT
Platform: UNKNOWN
Classifier: License :: OSI Approved :: MIT License
Classifier: Development Status :: 3 - Alpha
Classifier: Intended Audience :: Developers
Classifier: Topic :: Software Development :: Build Tools
Classifier: Programming Language :: Python :: 2
Classifier: Programming Language :: Python :: 2.6
Classifier: Programming Language :: Python :: 2.7
Requires-Dist: fabric (>=1.1.0,<2.0.0)
